[
  {"farmaco": "R1","cantidad": "01","accion": "Desintoxicación al favorecer procesos de excreción por todas las membranas mucosas, inmunomodulación para trastornos agudos y crónicos."},
  {"farmaco": "R6","cantidad": "01","accion": "Indicación en virosis respiratoria alta. lnmuno estimulador en caso de enfermedades virales."},
  {"farmaco": "R49","cantidad": "01","accion": "Catarros agudos y crónicos de los senos nasales, frontales y maxilares.\nPrevencion de complicaciones de V.R.A."},
  {"farmaco": "R17","cantidad": "01","accion": "Acción sobre el sistema linfático en el sentido de una terapia de drenaje."}
]